pytest_neos/__init__.py
pytest_neos-0.1.2.dist-info/METADATA
pytest_neos-0.1.2.dist-info/WHEEL
pytest_neos-0.1.2.dist-info/entry_points.txt
pytest_neos-0.1.2.dist-info/RECORD
